simplemp/__init__.py
simplemp/info.py
simplemp/logs.py
simplemp/simplemp.py
simplemp/simplempcore.py
simplemp/validator.py
simplemp-0.7.5.dist-info/licenses/LICENSE
simplemp-0.7.5.dist-info/METADATA
simplemp-0.7.5.dist-info/WHEEL
simplemp-0.7.5.dist-info/top_level.txt
simplemp-0.7.5.dist-info/RECORD
