Metadata-Version: 2.4
Name: simplemp
Version: 0.7.5
Summary: Python-first media processing API
Author-email: "S.M Sadat" <smsadat788@gmail.com>
License: The MIT License (MIT)
Project-URL: Homepage, https://github.com/XST-BD/SimpleMP/tree/main
Project-URL: Documentation, https://github.com/XST-BD/SimpleMP/tree/main/docs
Project-URL: Source, https://github.com/XST-BD/SimpleMP/tree/main
Project-URL: Issues, https://github.com/XST-BD/SimpleMP/tree/main
Requires-Python: >=3.8
License-File: LICENSE
Requires-Dist: av>=10.0.0
Requires-Dist: typeguard>=4.0.0
Dynamic: license-file
